rocketpay/__init__.py
rocketpay/api_client.py
rocketpay/configuration.py
rocketpay/rest.py
rocketpay/api/__init__.py
rocketpay/api/app_api.py
rocketpay/api/currencies_api.py
rocketpay/api/multi_cheques_api.py
rocketpay/api/subscriptions_api.py
rocketpay/api/tg_invoices_api.py
rocketpay/api/version_api.py
rocketpay/models/__init__.py
rocketpay/models/all_of_cheque_disabled_languages.py
rocketpay/models/all_of_coin_dto_fee_withdraw.py
rocketpay/models/all_of_pay_invoice_dto_payment.py
rocketpay/models/all_of_short_cheque_dto_disabled_languages.py
rocketpay/models/all_of_subscription_interval.py
rocketpay/models/all_of_subscription_tg_resource.py
rocketpay/models/api_bad_request_error.py
rocketpay/models/api_error.py
rocketpay/models/app.py
rocketpay/models/app_balance.py
rocketpay/models/app_dto.py
rocketpay/models/available_coins.py
rocketpay/models/available_coins_data.py
rocketpay/models/check_subscription_dto.py
rocketpay/models/cheque.py
rocketpay/models/coin_dto.py
rocketpay/models/create_cheque_dto.py
rocketpay/models/create_invoice_dto.py
rocketpay/models/create_subscription_dto.py
rocketpay/models/create_transfer_dto.py
rocketpay/models/create_withdrawal_dto.py
rocketpay/models/delete_response_dto.py
rocketpay/models/edit_subscription_interval_dto.py
rocketpay/models/full_invoice_dto.py
rocketpay/models/full_invoice_response_dto.py
rocketpay/models/invoice.py
rocketpay/models/paginated_invoice_response.py
rocketpay/models/paginated_short_cheque_dto_response.py
rocketpay/models/paginated_subscription_response.py
rocketpay/models/pagination_dto.py
rocketpay/models/pay_invoice_dto.py
rocketpay/models/pay_invoice_stat_dto.py
rocketpay/models/property_error.py
rocketpay/models/rates.py
rocketpay/models/response_dto.py
rocketpay/models/set.py
rocketpay/models/short_cheque_dto.py
rocketpay/models/simple_cheque_response.py
rocketpay/models/simple_full_invoice_dto_response.py
rocketpay/models/simple_invoice_response.py
rocketpay-1.0.1.dist-info/METADATA
rocketpay-1.0.1.dist-info/WHEEL
rocketpay-1.0.1.dist-info/top_level.txt
rocketpay-1.0.1.dist-info/RECORD
