Metadata-Version: 2.1
Name: rocketpay
Version: 1.0.1
Summary: TON Rocket Pay API
Home-page: https://pay.ton-rocket.com/api/
Author-email: 
License: MIT license
Keywords: TON Rocket Pay API,python client
Classifier: Development Status :: 2 - Pre-Alpha
Classifier: Intended Audience :: Developers
Classifier: License :: OSI Approved :: MIT License
Classifier: Natural Language :: English
Classifier: Programming Language :: Python :: 3
Classifier: Programming Language :: Python :: 3.7
Classifier: Programming Language :: Python :: 3.8
Classifier: Programming Language :: Python :: 3.9
Requires-Dist: urllib3 (>=1.15)
Requires-Dist: six (>=1.10)
Requires-Dist: certifi
Requires-Dist: python-dateutil
